opendxmc/__init__.py
opendxmc/utils.py
opendxmc/app/__init__.py
opendxmc/app/copy_icon.png
opendxmc/app/dicom_lut.py
opendxmc/app/ffmpeg_writer.py
opendxmc/app/gui.py
opendxmc/app/icon.png
opendxmc/app/model.py
opendxmc/app/splash_loading.png
opendxmc/app/start.py
opendxmc/app/view.py
opendxmc/data/__init__.py
opendxmc/data/phantom_definitions.py
opendxmc/data/materials/densities.txt
opendxmc/data/materials/organics.txt
opendxmc/data/materials/attenuation/adipose
opendxmc/data/materials/attenuation/air.txt
opendxmc/data/materials/attenuation/blood.txt
opendxmc/data/materials/attenuation/hardbone.txt
opendxmc/data/materials/attenuation/iodine.txt
opendxmc/data/materials/attenuation/lead.txt
opendxmc/data/materials/attenuation/lung.txt
opendxmc/data/materials/attenuation/muscle.txt
opendxmc/data/materials/attenuation/pmma.txt
opendxmc/data/materials/attenuation/redbonemarrow.txt
opendxmc/data/materials/attenuation/skin.txt
opendxmc/data/materials/attenuation/soft.txt
opendxmc/data/materials/attenuation/water.txt
opendxmc/data/materials/attenuation/yellowbonemarrow.txt
opendxmc/database/__init__.py
opendxmc/database/dicom_importer.py
opendxmc/database/h5database.py
opendxmc/database/import_materials.py
opendxmc/database/import_phantoms.py
opendxmc/engine/__init__.py
opendxmc/engine/enginelib.py
opendxmc/engine/enginelib32.dll
opendxmc/engine/enginelib32.so
opendxmc/engine/enginelib64.dll
opendxmc/engine/enginelib64.so
opendxmc/engine/src/compileCommandsGcc
opendxmc/engine/src/enginelib.c
opendxmc/engine/src/enginelib.h
opendxmc/engine/src/enginelib.o
opendxmc/engine/src/enginelib.sdf
opendxmc/engine/src/enginelib.sln
opendxmc/engine/src/enginelib.v12.suo
opendxmc/engine/src/enginelib.vcxproj
opendxmc/engine/src/enginelib.vcxproj.filters
opendxmc/engine/src/enginelib.vcxproj.user
opendxmc/engine/src/enginelibCUDAbroken.c
opendxmc/engine/src/enginetest.c
opendxmc/materials/__init__.py
opendxmc/materials/materials.py
opendxmc-0.3.8.dist-info/METADATA
opendxmc-0.3.8.dist-info/RECORD
opendxmc-0.3.8.dist-info/WHEEL
opendxmc-0.3.8.dist-info/top_level.txt
